{
    "0": [
        "people",
        "like",
        "going",
        "want",
        "really",
        "think",
        "thing",
        "make",
        "say",
        "right",
        "kid",
        "fuck",
        "shit",
        "die",
        "look"
    ],
    "1": [
        "life",
        "month",
        "open",
        "love",
        "live",
        "teacher",
        "student",
        "business",
        "patient",
        "started",
        "cyrilramaphosa",
        "doctor",
        "use",
        "watching",
        "thinking"
    ],
    "2": [
        "social",
        "distancing",
        "test",
        "getting",
        "care",
        "disney",
        "hospital",
        "place",
        "dr",
        "sure",
        "risk",
        "result",
        "took",
        "restaurant",
        "alcohol"
    ],
    "3": [
        "come",
        "help",
        "great",
        "vaccine",
        "tomorrow",
        "wont",
        "seen",
        "response",
        "outbreak",
        "flu",
        "night",
        "second",
        "finally",
        "park",
        "political"
    ],
    "4": [
        "trump",
        "virus",
        "world",
        "country",
        "government",
        "american",
        "fauci",
        "tell",
        "president",
        "america",
        "believe",
        "spread",
        "plan",
        "taking",
        "point"
    ],
    "5": [
        "got",
        "week",
        "tested",
        "positive",
        "said",
        "away",
        "party",
        "guy",
        "went",
        "thought",
        "told",
        "god",
        "actually",
        "health",
        "wait"
    ],
    "6": [
        "case",
        "new",
        "day",
        "death",
        "florida",
        "today",
        "state",
        "number",
        "news",
        "total",
        "reported",
        "testing",
        "record",
        "daily",
        "hour"
    ],
    "7": [
        "home",
        "stay",
        "year",
        "way",
        "let",
        "child",
        "safe",
        "bc",
        "cause",
        "died",
        "remember",
        "2020",
        "old",
        "maybe",
        "lost"
    ],
    "8": [
        "mask",
        "wear",
        "know",
        "dont",
        "wearing",
        "family",
        "fucking",
        "friend",
        "stop",
        "public",
        "mean",
        "face",
        "man",
        "house",
        "hard"
    ],
    "9": [
        "pandemic",
        "lockdown",
        "time",
        "school",
        "need",
        "work",
        "good",
        "feel",
        "job",
        "end",
        "real",
        "better",
        "bad",
        "hope",
        "long"
    ]
}
