{
    "1": {
        "features": {
            "need": 1.1110337398366863,
            "pandemic": 1.071559735929049,
            "help": 1.0009312876006655,
            "worker": 0.9306860452209248,
            "community": 0.9115725225417681,
            "work": 0.806996656389237,
            "health": 0.7559483045934029,
            "support": 0.720877701389874,
            "time": 0.6855940537231189,
            "people": 0.6848549399512975,
            "safe": 0.6771516897262703,
            "good": 0.6536588429990172,
            "make": 0.6377342405087351,
            "child": 0.6269860592995836,
            "story": 0.5863333928553701
        },
        "words": [
            "need",
            "pandemic",
            "help",
            "worker",
            "community",
            "work",
            "health",
            "support",
            "time",
            "people",
            "safe",
            "good",
            "make",
            "child",
            "story"
        ],
        "coherence": 0.4852258134455908
    },
    "2": {
        "features": {
            "case": 4.908106600021316,
            "new": 4.689995629185785,
            "death": 2.9120177754746055,
            "number": 1.6730454180540435,
            "ontario": 1.5219161870858098,
            "day": 1.4178262605484437,
            "test": 1.2734591894622231,
            "positive": 1.2044028217387965,
            "june": 1.1817866044047707,
            "breaking": 1.1384020986786225,
            "report": 1.1047213329504582,
            "total": 1.0602522194280766,
            "today": 1.0353458608283104,
            "outbreak": 0.966803004909383,
            "reported": 0.9416726218775172
        },
        "words": [
            "case",
            "new",
            "death",
            "number",
            "ontario",
            "day",
            "test",
            "positive",
            "june",
            "breaking",
            "report",
            "total",
            "today",
            "outbreak",
            "reported"
        ],
        "coherence": 0.5042632962976183
    },
    "3": {
        "features": {
            "social": 4.8685998500076435,
            "distancing": 4.502898700682948,
            "rule": 1.2578097739141207,
            "protest": 1.1042431154926045,
            "gathering": 1.05342486550496,
            "hand": 1.0460607686501024,
            "park": 0.7934888855604069,
            "funeral": 0.7802645448950072,
            "justintrudeau": 0.7756869068073029,
            "physical": 0.7544393627935597,
            "open": 0.7471235822531951,
            "crowd": 0.7157768118215145,
            "attend": 0.6827841672571417,
            "large": 0.6770433378063904,
            "allowed": 0.6440230026162652
        },
        "words": [
            "social",
            "distancing",
            "rule",
            "protest",
            "gathering",
            "hand",
            "park",
            "funeral",
            "justintrudeau",
            "physical",
            "open",
            "crowd",
            "attend",
            "large",
            "allowed"
        ],
        "coherence": 0.5179113209247589
    },
    "4": {
        "features": {
            "mask": 4.137591458692628,
            "spread": 2.35792224186911,
            "say": 1.8894607135396502,
            "day": 1.6679288232248084,
            "face": 1.421703142559659,
            "away": 1.3860263280899656,
            "wear": 1.3817013868356773,
            "asymptomatic": 1.2741853617528174,
            "visit": 1.2525182371520638,
            "line": 1.2198993913381777,
            "wearing": 1.1819042828443407,
            "trump": 1.1099441293989696,
            "rare": 0.9471417902741809,
            "evidence": 0.865223784158517,
            "transmission": 0.8287410796766087
        },
        "words": [
            "mask",
            "spread",
            "say",
            "day",
            "face",
            "away",
            "wear",
            "asymptomatic",
            "visit",
            "line",
            "wearing",
            "trump",
            "rare",
            "evidence",
            "transmission"
        ],
        "coherence": 0.4643234400522141
    },
    "5": {
        "features": {
            "trump": 3.144291646772848,
            "pandemic": 2.237631680158492,
            "american": 1.9230177035650189,
            "president": 1.6351846378692483,
            "realdonaldtrump": 1.5190813048900116,
            "america": 1.092701351309544,
            "riot": 0.8259137509543464,
            "state": 0.7942564128882369,
            "dead": 0.7864328689540812,
            "100000": 0.7520193225351097,
            "great": 0.7254334404901162,
            "million": 0.6786782633962419,
            "vote": 0.6654544885911607,
            "death": 0.6454967624727627,
            "country": 0.641037701803543
        },
        "words": [
            "trump",
            "pandemic",
            "american",
            "president",
            "realdonaldtrump",
            "america",
            "riot",
            "state",
            "dead",
            "100000",
            "great",
            "million",
            "vote",
            "death",
            "country"
        ],
        "coherence": 0.48454417302494956
    },
    "6": {
        "features": {
            "people": 2.8023928609084434,
            "protest": 2.6175273624849704,
            "black": 1.5717382897689673,
            "police": 1.5672871816260394,
            "week": 1.1213779287469257,
            "protester": 1.0830691137448913,
            "going": 1.0805574068485424,
            "thousand": 1.0786477523973688,
            "think": 1.0171817721010514,
            "know": 0.8659650000937702,
            "ago": 0.8508568910154605,
            "right": 0.8389398988169409,
            "white": 0.836574021943746,
            "matter": 0.8287414906232905,
            "really": 0.8172055662024931
        },
        "words": [
            "people",
            "protest",
            "black",
            "police",
            "week",
            "protester",
            "going",
            "thousand",
            "think",
            "know",
            "ago",
            "right",
            "white",
            "matter",
            "really"
        ],
        "coherence": 0.5005518436431885
    },
    "7": {
        "features": {
            "pandemic": 3.195083561273955,
            "way": 2.0708950228405922,
            "ableg": 1.1270750430258505,
            "government": 1.102061243436432,
            "minister": 1.1016426624066775,
            "federal": 1.0694612242420352,
            "amid": 0.9437823637973872,
            "restaurant": 0.9061545485790143,
            "canadian": 0.8825209356643401,
            "leave": 0.8767375194075834,
            "watch": 0.847779381714668,
            "hold": 0.7923807132505927,
            "crisis": 0.7892663130690736,
            "party": 0.7859928867001615,
            "hell": 0.7649755649543126
        },
        "words": [
            "pandemic",
            "way",
            "ableg",
            "government",
            "minister",
            "federal",
            "amid",
            "restaurant",
            "canadian",
            "leave",
            "watch",
            "hold",
            "crisis",
            "party",
            "hell"
        ],
        "coherence": 0.4372162933860506
    },
    "8": {
        "features": {
            "lockdown": 4.130820544231644,
            "china": 1.5848970778564975,
            "control": 1.1962620180261176,
            "virus": 1.146646426708033,
            "restriction": 1.092605334199772,
            "uk": 0.7962399646148749,
            "order": 0.7541867862646341,
            "border": 0.7185363337908682,
            "news": 0.7177192824784623,
            "closed": 0.7154086671574055,
            "scientist": 0.6950195196752428,
            "long": 0.6873049321681495,
            "economy": 0.6536472202754321,
            "fordnation": 0.6435521583367906,
            "country": 0.6363035045141779
        },
        "words": [
            "lockdown",
            "china",
            "control",
            "virus",
            "restriction",
            "uk",
            "order",
            "border",
            "news",
            "closed",
            "scientist",
            "long",
            "economy",
            "fordnation",
            "country"
        ],
        "coherence": 0.4375044388430459
    },
    "9": {
        "features": {
            "home": 3.4416991944723687,
            "stay": 2.372195930830836,
            "trudeau": 2.031294148867826,
            "care": 1.7684268206839509,
            "canadian": 1.69991068537962,
            "cdnpoli": 1.4303425225043742,
            "life": 1.3556429471601488,
            "canada": 1.224900505848085,
            "onpoli": 0.9806002392242515,
            "senior": 0.9354153727949379,
            "pm": 0.9086261138519999,
            "save": 0.8499472221337201,
            "parliament": 0.8207106027496521,
            "ford": 0.7754355018451432,
            "longterm": 0.7258225575239056
        },
        "words": [
            "home",
            "stay",
            "trudeau",
            "care",
            "canadian",
            "cdnpoli",
            "life",
            "canada",
            "onpoli",
            "senior",
            "pm",
            "save",
            "parliament",
            "ford",
            "longterm"
        ],
        "coherence": 0.4338588786976678
    },
    "10": {
        "features": {
            "le": 1.7655838607644108,
            "dr": 1.5934964670669354,
            "health": 1.5576790472302908,
            "data": 1.0600554194487604,
            "update": 1.0333577714378113,
            "et": 0.9689092757085123,
            "study": 0.952758996878974,
            "disease": 0.7537647343706255,
            "pour": 0.712396529993329,
            "henry": 0.6482582817427854,
            "hydroxychloroquine": 0.6469196344039538,
            "du": 0.6315650262559628,
            "au": 0.6125879746952896,
            "medical": 0.5499658843288331,
            "plus": 0.5178422625276922
        },
        "words": [
            "le",
            "dr",
            "health",
            "data",
            "update",
            "et",
            "study",
            "disease",
            "pour",
            "henry",
            "hydroxychloroquine",
            "du",
            "au",
            "medical",
            "plus"
        ],
        "coherence": 0.3413995623588562
    }
}
